.DS_Store
grape/__init__.py
grape/diagnostics.py
grape/hyperparameter_optimizer.py
grape/interpret.py
grape/model_utils.py
grape/param_space.py
grape/preprocessor.py
grape/regression_model.py
grape/tests.py
grape/utils.py
grape_model-0.0.3.dist-info/LICENSE
grape_model-0.0.3.dist-info/METADATA
grape_model-0.0.3.dist-info/WHEEL
grape_model-0.0.3.dist-info/top_level.txt
grape_model-0.0.3.dist-info/RECORD
